nGPT_pytorch/__init__.py
nGPT_pytorch/evo.py
nGPT_pytorch/nGPT.py
nGPT_pytorch/nGPTExperimental.py
nGPT_pytorch/nTransformer.py
ngpt_pytorch-0.2.16.dist-info/METADATA
ngpt_pytorch-0.2.16.dist-info/WHEEL
ngpt_pytorch-0.2.16.dist-info/licenses/LICENSE
ngpt_pytorch-0.2.16.dist-info/RECORD
