Metadata-Version: 2.4
Name: nGPT-pytorch
Version: 0.2.16
Summary: nGPT
Project-URL: Homepage, https://pypi.org/project/nGPT-pytorch/
Project-URL: Repository, https://github.com/lucidrains/nGPT-pytorch
Author-email: Phil Wang <lucidrains@gmail.com>
License: MIT License
License-File: LICENSE
Keywords: artificial intelligence,attention mechanism,deep learning,hypersphere,transformer
Classifier: Development Status :: 4 - Beta
Classifier: Intended Audience :: Developers
Classifier: License :: OSI Approved :: MIT License
Classifier: Programming Language :: Python :: 3.9
Classifier: Topic :: Scientific/Engineering :: Artificial Intelligence
Requires-Python: >=3.9
Requires-Dist: einops>=0.8.0
Requires-Dist: rotary-embedding-torch
Requires-Dist: torch>=2.4
Provides-Extra: examples
Provides-Extra: test
Requires-Dist: pytest; extra == 'test'
